{
  "chapter": {
    "id": "lxx-greek:ezekiel.20",
    "translationId": "lxx-greek",
    "bookSlug": "ezekiel",
    "chapterNumber": 20,
    "referenceLabel": "Ezekiel 20",
    "summary": "Source text for Ezekiel 20 in Septuagint Greek."
  },
  "verses": [
    {
      "id": "lxx-greek:ezekiel.20.1",
      "translationId": "lxx-greek",
      "bookSlug": "ezekiel",
      "chapterNumber": 20,
      "verseNumber": 1,
      "referenceLabel": "Ezekiel 20:1",
      "text": "Και εν τω εβδομω ετει, τω πεμπτω μηνι, τη δεκατη του μηνος, ηλθον τινες εκ των πρεσβυτερων του Ισραηλ δια να επερωτησωσι τον Κυριον, και εκαθησαν εμπροσθεν μου.",
      "paragraphStart": true
    },
    {
      "id": "lxx-greek:ezekiel.20.2",
      "translationId": "lxx-greek",
      "bookSlug": "ezekiel",
      "chapterNumber": 20,
      "verseNumber": 2,
      "referenceLabel": "Ezekiel 20:2",
      "text": "Και εγεινε λογος Κυριου προς εμε, λεγων,",
      "paragraphStart": false
    },
    {
      "id": "lxx-greek:ezekiel.20.3",
      "translationId": "lxx-greek",
      "bookSlug": "ezekiel",
      "chapterNumber": 20,
      "verseNumber": 3,
      "referenceLabel": "Ezekiel 20:3",
      "text": "Υιε ανθρωπου, λαλησον προς τους πρεσβυτερους του Ισραηλ και ειπε προς αυτους, Ουτω λεγει Κυριος ο Θεος Ηλθετε δια να με επερωτησητε; Ζω εγω, λεγει Κυριος ο Θεος, δεν θελω επερωτηθη απο σας.",
      "paragraphStart": false
    },
    {
      "id": "lxx-greek:ezekiel.20.4",
      "translationId": "lxx-greek",
      "bookSlug": "ezekiel",
      "chapterNumber": 20,
      "verseNumber": 4,
      "referenceLabel": "Ezekiel 20:4",
      "text": "Θελεις κρινει αυτους; υιε ανθρωπου, θελεις κρινει; δειξον εις αυτους τα βδελυγματα των πατερων αυτων",
      "paragraphStart": false
    },
    {
      "id": "lxx-greek:ezekiel.20.5",
      "translationId": "lxx-greek",
      "bookSlug": "ezekiel",
      "chapterNumber": 20,
      "verseNumber": 5,
      "referenceLabel": "Ezekiel 20:5",
      "text": "και ειπε προς αυτους, Ουτω λεγει Κυριος ο Θεος Εν τη ημερα καθ' ην εξελεξα τον Ισραηλ και υψωσα την χειρα μου προς το σπερμα του οικου Ιακωβ και εγνωρισθην εις αυτους εν Αιγυπτω και υψωσα την χειρα μου προς αυτους, λεγων, Εγω ειμαι Κυριος ο Θεος σας,",
      "paragraphStart": false
    },
    {
      "id": "lxx-greek:ezekiel.20.6",
      "translationId": "lxx-greek",
      "bookSlug": "ezekiel",
      "chapterNumber": 20,
      "verseNumber": 6,
      "referenceLabel": "Ezekiel 20:6",
      "text": "εν εκεινη τη ημερα υψωσα την χειρα μου προς αυτους οτι θελω εξαγαγει αυτους εκ γης Αιγυπτου εις γην την οποιαν προεβλεψα δι' αυτους, γην ρεουσαν γαλα και μελι, ητις ειναι η δοξα πασων των γαιων.",
      "paragraphStart": false
    },
    {
      "id": "lxx-greek:ezekiel.20.7",
      "translationId": "lxx-greek",
      "bookSlug": "ezekiel",
      "chapterNumber": 20,
      "verseNumber": 7,
      "referenceLabel": "Ezekiel 20:7",
      "text": "Και ειπα προς αυτους, Απορριψατε εκαστος τα βδελυγματα των οφθαλμων αυτου και μη μιαινεσθε με τα ειδωλα της Αιγυπτου εγω ειμαι Κυριος ο Θεος σας.",
      "paragraphStart": false
    },
    {
      "id": "lxx-greek:ezekiel.20.8",
      "translationId": "lxx-greek",
      "bookSlug": "ezekiel",
      "chapterNumber": 20,
      "verseNumber": 8,
      "referenceLabel": "Ezekiel 20:8",
      "text": "Αυτοι ομως απεστατησαν απ' εμου και δεν ηθελησαν να μου ακουσωσι δεν απερριψαν εκαστος τα βδελυγματα των οφθαλμων αυτων και δεν εγκατελιπον τα ειδωλα της Αιγυπτου. Τοτε ειπα να εκχεω τον θυμον μου επ' αυτους, δια να συντελεσω την οργην μου εναντιον αυτων εν μεσω της γης Αιγυπτου.",
      "paragraphStart": false
    },
    {
      "id": "lxx-greek:ezekiel.20.9",
      "translationId": "lxx-greek",
      "bookSlug": "ezekiel",
      "chapterNumber": 20,
      "verseNumber": 9,
      "referenceLabel": "Ezekiel 20:9",
      "text": "Πλην ενεκεν του ονοματος μου, δια να μη βεβηλωθη ενωπιον των εθνων, μεταξυ των οποιων ησαν και εμπροσθεν των οποιων εγνωρισθην εις αυτους, εκαμον τουτο, να εξαγαγω αυτους εκ γης Αιγυπτου.",
      "paragraphStart": false
    },
    {
      "id": "lxx-greek:ezekiel.20.10",
      "translationId": "lxx-greek",
      "bookSlug": "ezekiel",
      "chapterNumber": 20,
      "verseNumber": 10,
      "referenceLabel": "Ezekiel 20:10",
      "text": "Και εξηγαγον αυτους εκ γης Αιγυπτου και εφερα αυτους εις την ερημον",
      "paragraphStart": false
    },
    {
      "id": "lxx-greek:ezekiel.20.11",
      "translationId": "lxx-greek",
      "bookSlug": "ezekiel",
      "chapterNumber": 20,
      "verseNumber": 11,
      "referenceLabel": "Ezekiel 20:11",
      "text": "και εδωκα εις αυτους τα διαταγματα μου και εκαμον εις αυτους γνωστας τας κρισεις μου, τας οποιας καμνων ο ανθρωπος θελει ζησει δι' αυτων.",
      "paragraphStart": false
    },
    {
      "id": "lxx-greek:ezekiel.20.12",
      "translationId": "lxx-greek",
      "bookSlug": "ezekiel",
      "chapterNumber": 20,
      "verseNumber": 12,
      "referenceLabel": "Ezekiel 20:12",
      "text": "Και τα σαββατα μου εδωκα ετι εις αυτους, δια να ηναι μεταξυ εμου και αυτων σημειον, ωστε να γνωριζωσιν οτι εγω ειμαι ο Κυριος ο αγιαζων αυτους.",
      "paragraphStart": false
    },
    {
      "id": "lxx-greek:ezekiel.20.13",
      "translationId": "lxx-greek",
      "bookSlug": "ezekiel",
      "chapterNumber": 20,
      "verseNumber": 13,
      "referenceLabel": "Ezekiel 20:13",
      "text": "Αλλ' ο οικος Ισραηλ απεστατησεν απ' εμου εν τη ερημω εν τοις διαταγμασι μου δεν περιεπατησαν και τας κρισεις μου απερριψαν, τας οποιας καμνων ο ανθρωπος θελει ζησει δι' αυτων και τα σαββατα μου εβεβηλωσαν σφοδρα τοτε ειπα να εκχεω τον θυμον μου επ' αυτους εν τη ερημω, δια να εξολοθρευσω αυτους.",
      "paragraphStart": false
    },
    {
      "id": "lxx-greek:ezekiel.20.14",
      "translationId": "lxx-greek",
      "bookSlug": "ezekiel",
      "chapterNumber": 20,
      "verseNumber": 14,
      "referenceLabel": "Ezekiel 20:14",
      "text": "Πλην εκαμον τουτο ενεκεν του ονοματος μου, δια να μη βεβηλωθη ενωπιον των εθνων, εμπροσθεν των οποιων εξηγαγον αυτους.",
      "paragraphStart": false
    },
    {
      "id": "lxx-greek:ezekiel.20.15",
      "translationId": "lxx-greek",
      "bookSlug": "ezekiel",
      "chapterNumber": 20,
      "verseNumber": 15,
      "referenceLabel": "Ezekiel 20:15",
      "text": "Και εγω υψωσα οτι προς αυτους την χειρα μου εν τη ερημω, οτι δεν θελω φερει αυτους εις την γην, την οποιαν εδωκα εις αυτους, γην ρεουσαν γαλα και μελι, ητις ειναι δοξα πασων των γαιων",
      "paragraphStart": false
    },
    {
      "id": "lxx-greek:ezekiel.20.16",
      "translationId": "lxx-greek",
      "bookSlug": "ezekiel",
      "chapterNumber": 20,
      "verseNumber": 16,
      "referenceLabel": "Ezekiel 20:16",
      "text": "διοτι τας κρισεις μου απερριψαν και εν τοις διαταγμασι μου δεν περιεπατησαν και τα σαββατα μου εβεβηλωσαν διοτι αι καρδιαι αυτων επορευοντο κατοπιν των ειδωλων αυτων.",
      "paragraphStart": false
    },
    {
      "id": "lxx-greek:ezekiel.20.17",
      "translationId": "lxx-greek",
      "bookSlug": "ezekiel",
      "chapterNumber": 20,
      "verseNumber": 17,
      "referenceLabel": "Ezekiel 20:17",
      "text": "Και εφεισθη ο οφθαλμος μου επ' αυτους, ωστε να μη εξαλειψω αυτους, και δεν συνετελεσα αυτους εν τη ερημω.",
      "paragraphStart": false
    },
    {
      "id": "lxx-greek:ezekiel.20.18",
      "translationId": "lxx-greek",
      "bookSlug": "ezekiel",
      "chapterNumber": 20,
      "verseNumber": 18,
      "referenceLabel": "Ezekiel 20:18",
      "text": "Αλλ' ειπα προς τα τεκνα αυτων εν τη ερημω, Μη περιπατειτε εν τοις διαταγμασι των πατερων σας και μη φυλαττετε τας κρισεις αυτων και μη μιαινεσθε με τα ειδωλα αυτων",
      "paragraphStart": false
    },
    {
      "id": "lxx-greek:ezekiel.20.19",
      "translationId": "lxx-greek",
      "bookSlug": "ezekiel",
      "chapterNumber": 20,
      "verseNumber": 19,
      "referenceLabel": "Ezekiel 20:19",
      "text": "εγω ειμαι Κυριος ο Θεος σας εν τοις διαταγμασι μου περιπατειτε και τας κρισεις μου φυλαττετε και εκτελειτε αυτας",
      "paragraphStart": false
    },
    {
      "id": "lxx-greek:ezekiel.20.20",
      "translationId": "lxx-greek",
      "bookSlug": "ezekiel",
      "chapterNumber": 20,
      "verseNumber": 20,
      "referenceLabel": "Ezekiel 20:20",
      "text": "και αγιαζετε τα σαββατα μου, και ας ηναι μεταξυ εμου και υμων σημειον, ωστε να γνωριζητε οτι εγω ειμαι Κυριος ο Θεος σας.",
      "paragraphStart": false
    },
    {
      "id": "lxx-greek:ezekiel.20.21",
      "translationId": "lxx-greek",
      "bookSlug": "ezekiel",
      "chapterNumber": 20,
      "verseNumber": 21,
      "referenceLabel": "Ezekiel 20:21",
      "text": "Τα τεκνα ομως απεστατησαν απ' εμου εν τοις διαταγμασι μου δεν περιεπατησαν και τας κρισεις μου δεν εφυλαξαν, ωστε να εκτελωσιν αυτας, τας οποιας καμνων ο ανθρωπος θελει ζησει δι' αυτων τα σαββατα μου εβεβηλωσαν τοτε ειπα να εκχεω τον θυμον μου επ' αυτους, δια να συντελεσω την οργην μου εναντιον αυτων εν τη ερημω.",
      "paragraphStart": false
    },
    {
      "id": "lxx-greek:ezekiel.20.22",
      "translationId": "lxx-greek",
      "bookSlug": "ezekiel",
      "chapterNumber": 20,
      "verseNumber": 22,
      "referenceLabel": "Ezekiel 20:22",
      "text": "Και απεστρεψα την χειρα μου και εκαμον τουτο ενεκεν του ονοματος μου, δια να μη βεβηλωθη ενωπιον των εθνων, εμπροσθεν των οποιων εξηγαγον αυτους.",
      "paragraphStart": false
    },
    {
      "id": "lxx-greek:ezekiel.20.23",
      "translationId": "lxx-greek",
      "bookSlug": "ezekiel",
      "chapterNumber": 20,
      "verseNumber": 23,
      "referenceLabel": "Ezekiel 20:23",
      "text": "Υψωσα ετι εγω την χειρα μου προς αυτους εν τη ερημω, οτι ηθελον διασκορπισει αυτους μεταξυ των εθνων και διασπειρει αυτους εις τους τοπους",
      "paragraphStart": false
    },
    {
      "id": "lxx-greek:ezekiel.20.24",
      "translationId": "lxx-greek",
      "bookSlug": "ezekiel",
      "chapterNumber": 20,
      "verseNumber": 24,
      "referenceLabel": "Ezekiel 20:24",
      "text": "διοτι τας κρισεις μου δεν εξετελεσαν και τα διαταγματα μου απερριψαν και τα σαββατα μου εβεβηλωσαν, και οι οφθαλμοι αυτων ησαν κατοπιν των ειδωλων των πατερων αυτων.",
      "paragraphStart": false
    },
    {
      "id": "lxx-greek:ezekiel.20.25",
      "translationId": "lxx-greek",
      "bookSlug": "ezekiel",
      "chapterNumber": 20,
      "verseNumber": 25,
      "referenceLabel": "Ezekiel 20:25",
      "text": "Δια τουτο και εγω εδωκα εις αυτους διαταγματα ουχι καλα και κρισεις, δια των οποιων δεν ηθελον ζησει",
      "paragraphStart": false
    },
    {
      "id": "lxx-greek:ezekiel.20.26",
      "translationId": "lxx-greek",
      "bookSlug": "ezekiel",
      "chapterNumber": 20,
      "verseNumber": 26,
      "referenceLabel": "Ezekiel 20:26",
      "text": "και εμιανα αυτους εις τας προσφορας αυτων, εις το οτι διεβιβαζον δια του πυρος παν διανοιγον μητραν, δια να ερημωσω αυτους, ωστε να γνωρισωσιν οτι εγω ειμαι ο Κυριος.",
      "paragraphStart": false
    },
    {
      "id": "lxx-greek:ezekiel.20.27",
      "translationId": "lxx-greek",
      "bookSlug": "ezekiel",
      "chapterNumber": 20,
      "verseNumber": 27,
      "referenceLabel": "Ezekiel 20:27",
      "text": "Δια τουτο, υιε ανθρωπου, λαλησον προς τον οικον Ισραηλ και ειπε προς αυτους, Ουτω λεγει Κυριος ο Θεος κατα τουτο οτι οι πατερες σας υβρισαν εις εμε, καμνοντες παραβασιν εναντιον μου.",
      "paragraphStart": false
    },
    {
      "id": "lxx-greek:ezekiel.20.28",
      "translationId": "lxx-greek",
      "bookSlug": "ezekiel",
      "chapterNumber": 20,
      "verseNumber": 28,
      "referenceLabel": "Ezekiel 20:28",
      "text": "Διοτι αφου εφερα αυτους εις την γην, περι της οποιας υψωσα την χειρα μου οτι θελω δωσει αυτην εις αυτους, τοτε ενεβλεψαν εις παντα λοφον υψηλον και εις παν δενδρον κατασκιον, και εκει προσεφεραν τας θυσιας αυτων και εστησαν εκει τας παροργιστικας προσφορας αυτων, και εθεσαν εκει οσμην ευωδιας αυτων και εκαμον εκει τας σπονδας αυτων.",
      "paragraphStart": false
    },
    {
      "id": "lxx-greek:ezekiel.20.29",
      "translationId": "lxx-greek",
      "bookSlug": "ezekiel",
      "chapterNumber": 20,
      "verseNumber": 29,
      "referenceLabel": "Ezekiel 20:29",
      "text": "Και ειπα προς αυτους, Τι δηλοι ο υψηλος τοπος, εις τον οποιον σεις υπαγετε; και το ονομα αυτου εκληθη Βαμα, εως της σημερον.",
      "paragraphStart": false
    },
    {
      "id": "lxx-greek:ezekiel.20.30",
      "translationId": "lxx-greek",
      "bookSlug": "ezekiel",
      "chapterNumber": 20,
      "verseNumber": 30,
      "referenceLabel": "Ezekiel 20:30",
      "text": "Δια τουτο ειπε προς τον οικον Ισραηλ, Ουτω λεγει Κυριος ο Θεος Ενω σεις μιαινεσθε εν τη οδω των πατερων σας και εκπορνευετε κατοπιν των βδελυγματων αυτων",
      "paragraphStart": false
    },
    {
      "id": "lxx-greek:ezekiel.20.31",
      "translationId": "lxx-greek",
      "bookSlug": "ezekiel",
      "chapterNumber": 20,
      "verseNumber": 31,
      "referenceLabel": "Ezekiel 20:31",
      "text": "και μιαινεσθε με παντα τα ειδωλα σας εως της σημερον, προσφεροντες τα δωρα σας, διαβιβαζοντες τους υιους σας δια του πυρος, και εγω θελω επερωτηθη απο σας, οικος Ισραηλ; Ζω εγω, λεγει Κυριος ο Θεος, δεν θελω επερωτηθη απο σας.",
      "paragraphStart": false
    },
    {
      "id": "lxx-greek:ezekiel.20.32",
      "translationId": "lxx-greek",
      "bookSlug": "ezekiel",
      "chapterNumber": 20,
      "verseNumber": 32,
      "referenceLabel": "Ezekiel 20:32",
      "text": "Και εκεινο το οποιον διαβουλευεσθε, ουδολως θελει γεινει διοτι σεις λεγετε, Θελομεν εισθαι ως τα εθνη, ως αι οικογενειαι των τοπων, εις το να λατρευωμεν ξυλα και λιθους.",
      "paragraphStart": false
    },
    {
      "id": "lxx-greek:ezekiel.20.33",
      "translationId": "lxx-greek",
      "bookSlug": "ezekiel",
      "chapterNumber": 20,
      "verseNumber": 33,
      "referenceLabel": "Ezekiel 20:33",
      "text": "Ζω εγω, λεγει Κυριος ο Θεος, εξαπαντος εν χειρι κραταια και εν βραχιονι εξηπλωμενω και εν θυμω εκχεομενω θελω βασιλευσει εφ' υμας.",
      "paragraphStart": false
    },
    {
      "id": "lxx-greek:ezekiel.20.34",
      "translationId": "lxx-greek",
      "bookSlug": "ezekiel",
      "chapterNumber": 20,
      "verseNumber": 34,
      "referenceLabel": "Ezekiel 20:34",
      "text": "Και θελω σας εξαγαγει εκ των λαων και θελω σας συναξει εκ των τοπων, εις τους οποιους εισθε διεσκορπισμενοι, εν χειρι κραταια και εν βραχιονι εξηπλωμενω και εν θυμω εκχεομενω.",
      "paragraphStart": false
    },
    {
      "id": "lxx-greek:ezekiel.20.35",
      "translationId": "lxx-greek",
      "bookSlug": "ezekiel",
      "chapterNumber": 20,
      "verseNumber": 35,
      "referenceLabel": "Ezekiel 20:35",
      "text": "Και θελω σας φερει εις την ερημον των λαων και εκει θελω κριθη με σας προσωπον προς προσωπον",
      "paragraphStart": false
    },
    {
      "id": "lxx-greek:ezekiel.20.36",
      "translationId": "lxx-greek",
      "bookSlug": "ezekiel",
      "chapterNumber": 20,
      "verseNumber": 36,
      "referenceLabel": "Ezekiel 20:36",
      "text": "καθως εκριθην με τους πατερας σας εν τη ερημω της γης Αιγυπτου, ουτω θελω σας κρινει, λεγει Κυριος ο Θεος.",
      "paragraphStart": false
    },
    {
      "id": "lxx-greek:ezekiel.20.37",
      "translationId": "lxx-greek",
      "bookSlug": "ezekiel",
      "chapterNumber": 20,
      "verseNumber": 37,
      "referenceLabel": "Ezekiel 20:37",
      "text": "Και θελω σας περασει υπο την ραβδον και θελω σας φερει εις τους δεσμους της διαθηκης.",
      "paragraphStart": false
    },
    {
      "id": "lxx-greek:ezekiel.20.38",
      "translationId": "lxx-greek",
      "bookSlug": "ezekiel",
      "chapterNumber": 20,
      "verseNumber": 38,
      "referenceLabel": "Ezekiel 20:38",
      "text": "Και θελω εκκαθαρισει εκ μεσου υμων τους αποστατας και τους ασεβησαντας εις εμε θελω εκβαλει αυτους εκ της γης της παροικιας αυτων και δεν θελουσιν εισελθει εις γην Ισραηλ, και θελετε γνωρισει οτι εγω ειμαι ο Κυριος.",
      "paragraphStart": false
    },
    {
      "id": "lxx-greek:ezekiel.20.39",
      "translationId": "lxx-greek",
      "bookSlug": "ezekiel",
      "chapterNumber": 20,
      "verseNumber": 39,
      "referenceLabel": "Ezekiel 20:39",
      "text": "Σεις δε, οικος Ισραηλ, ουτω λεγει Κυριος ο Θεος Υπαγετε, λατρευετε εκαστος τα ειδωλα αυτου, και του λοιπου, εαν δεν θελητε να μου ακουητε και μη βεβηλονετε πλεον το ονομα μου το αγιον με τα δωρα σας και με τα ειδωλα σας.",
      "paragraphStart": false
    },
    {
      "id": "lxx-greek:ezekiel.20.40",
      "translationId": "lxx-greek",
      "bookSlug": "ezekiel",
      "chapterNumber": 20,
      "verseNumber": 40,
      "referenceLabel": "Ezekiel 20:40",
      "text": "Διοτι επι του ορους του αγιου μου, επι του υψηλου ορους του Ισραηλ, λεγει Κυριος ο Θεος, εκει πας ο οικος του Ισραηλ, παντες οι εν τη γη θελουσι με λατρευσει εκει θελω δεχθη αυτους και εκει θελω ζητησει τας προσφορας σας και τας απαρχας των δωρων σας με παντα τα αγια σας.",
      "paragraphStart": false
    },
    {
      "id": "lxx-greek:ezekiel.20.41",
      "translationId": "lxx-greek",
      "bookSlug": "ezekiel",
      "chapterNumber": 20,
      "verseNumber": 41,
      "referenceLabel": "Ezekiel 20:41",
      "text": "Θελω σας δεχθη με οσμην ευωδιας, οταν σας εξαγαγω εκ των λαων και σας συναξω εκ των τοπων εις τους οποιους διεσκορπισθητε και θελω αγιασθη εις εσας ενωπιον των εθνων.",
      "paragraphStart": false
    },
    {
      "id": "lxx-greek:ezekiel.20.42",
      "translationId": "lxx-greek",
      "bookSlug": "ezekiel",
      "chapterNumber": 20,
      "verseNumber": 42,
      "referenceLabel": "Ezekiel 20:42",
      "text": "Και θελετε γνωρισει οτι εγω ειμαι ο Κυριος, οταν σας φερω εις γην Ισραηλ, εις γην περι της οποιας υψωσα την χειρα μου οτι θελω δωσει αυτην εις τους πατερας σας.",
      "paragraphStart": false
    },
    {
      "id": "lxx-greek:ezekiel.20.43",
      "translationId": "lxx-greek",
      "bookSlug": "ezekiel",
      "chapterNumber": 20,
      "verseNumber": 43,
      "referenceLabel": "Ezekiel 20:43",
      "text": "Και εκει θελετε ενθυμηθη τας οδους σας και παντα τα εργα σας, εις τα οποια εμιανθητε και θελετε αποστραφη αυτοι εαυτους εμπροσθεν των οφθαλμων σας, δια παντα τα κακα σας οσα επραξατε.",
      "paragraphStart": false
    },
    {
      "id": "lxx-greek:ezekiel.20.44",
      "translationId": "lxx-greek",
      "bookSlug": "ezekiel",
      "chapterNumber": 20,
      "verseNumber": 44,
      "referenceLabel": "Ezekiel 20:44",
      "text": "Και θελετε γνωρισει οτι εγω ειμαι ο Κυριος, οταν καμω ουτως εις εσας ενεκεν του ονοματος μου, ουχι κατα τας πονηρας οδους σας ουδε κατα τα διεφθαρμενα εργα σας, οικος Ισραηλ, λεγει Κυριος ο Θεος.",
      "paragraphStart": false
    },
    {
      "id": "lxx-greek:ezekiel.20.45",
      "translationId": "lxx-greek",
      "bookSlug": "ezekiel",
      "chapterNumber": 20,
      "verseNumber": 45,
      "referenceLabel": "Ezekiel 20:45",
      "text": "Και εγεινε λογος Κυριου προς εμε, λεγων,",
      "paragraphStart": false
    },
    {
      "id": "lxx-greek:ezekiel.20.46",
      "translationId": "lxx-greek",
      "bookSlug": "ezekiel",
      "chapterNumber": 20,
      "verseNumber": 46,
      "referenceLabel": "Ezekiel 20:46",
      "text": "Υιε ανθρωπου, στηριξον το προσωπον σου προς μεσημβριαν και σταλαξον λογον προς μεσημβριαν και προφητευσον κατα του δασους της μεσημβρινης πεδιαδος",
      "paragraphStart": false
    },
    {
      "id": "lxx-greek:ezekiel.20.47",
      "translationId": "lxx-greek",
      "bookSlug": "ezekiel",
      "chapterNumber": 20,
      "verseNumber": 47,
      "referenceLabel": "Ezekiel 20:47",
      "text": "και ειπε προς το δασος της μεσημβριας, Ακουσον τον λογον του Κυριου Ουτω λεγει Κυριος ο Θεος Ιδου, εγω θελω αναψει πυρ εν σοι, και θελει καταφαγει εν σοι παν δενδρον χλωρον και παν δενδρον ξηρον η φλοξ η εξαφθεισα δεν θελει σβεσθη, και παν προσωπον απο μεσημβριας μεχρι βορρα θελει καυθη εν αυτω.",
      "paragraphStart": false
    },
    {
      "id": "lxx-greek:ezekiel.20.48",
      "translationId": "lxx-greek",
      "bookSlug": "ezekiel",
      "chapterNumber": 20,
      "verseNumber": 48,
      "referenceLabel": "Ezekiel 20:48",
      "text": "Και πασα σαρξ θελει ιδει, οτι εγω ο Κυριος εξεκαυσα αυτο δεν θελει σβεσθη.",
      "paragraphStart": false
    },
    {
      "id": "lxx-greek:ezekiel.20.49",
      "translationId": "lxx-greek",
      "bookSlug": "ezekiel",
      "chapterNumber": 20,
      "verseNumber": 49,
      "referenceLabel": "Ezekiel 20:49",
      "text": "Και εγω ειπα, Φευ Κυριε Θεε αυτοι λεγουσι περι εμου, δεν λαλει ουτος παροιμιας;",
      "paragraphStart": false
    }
  ]
}
