{
  "bookSlug": "genesis",
  "chapterNumber": 24,
  "entries": [
    {
      "id": "ephraim-commentary-genesis:genesis.24",
      "relation": "chapter",
      "targetChapterId": "genesis.24",
      "topicSlugs": [
        "scripture",
        "syrian-tradition",
        "typology"
      ],
      "personId": "ephraim-the-syrian",
      "workId": "ephraim-commentary-genesis",
      "title": "Ephraim the Syrian on Genesis 24",
      "excerpt": "Three years after the death of Sarah, “Abraham said to his eldest servant… Put thy hand under my thigh, and I will adjure thee… that thou shalt not take a wife for my son… of the daughters of the Canaanites” (Gen 24:2–3). The servant swears by the covenant of circumcision.…",
      "takeaway": "",
      "sourceId": "ephraim-commentary-genesis-source",
      "rank": 50,
      "tags": [
        "ephraim",
        "syrian",
        "genesis",
        "patristic"
      ]
    }
  ]
}
