{
  "bookSlug": "isaiah",
  "chapterNumber": 38,
  "verseNumber": 13,
  "entries": [
    {
      "id": "hcf:jerome:isaiah.38.13:b482754b:0",
      "relation": "verse",
      "topicSlugs": [],
      "personId": "jerome",
      "workId": "hcf:work:jerome:commentary-on-isaiah",
      "title": "Commentary on Isaiah on isaiah 38:13",
      "excerpt": "(Verse 13) I hoped until morning; like a lion, it has crushed all my bones. From morning until evening you will finish me. In the morning, he says, you will finish me until evening: I hoped until morning: which Job also says he endured in his distress and bodily torments (Job IV), when in daylight he awaited night, and in darkness awaited light, thinking that the punishments could be changed by the shifting of seasons. He knows this to be true who is burning with great fevers, whose internal fire, like that of a lion, consumes all his bones, and who does not think he will survive beyond the magnitude of his pain.",
      "takeaway": "",
      "sourceId": "hcf:source:historicalchristian-faith",
      "rank": 60,
      "tags": [
        "hcf",
        "c420"
      ],
      "targetVerseId": "kjva:isaiah.38.13"
    },
    {
      "id": "hcf:thomas-aquinas:isaiah.38.13:8b94bc29:0",
      "relation": "verse",
      "topicSlugs": [],
      "personId": "thomas-aquinas",
      "workId": "hcf:work:thomas-aquinas:commentary-on-isaiah",
      "title": "Commentary on Isaiah on isaiah 38:13",
      "excerpt": "776. Third, he laments his anxiety of heart.\r\n\r\nAnd first, as to the continual expectation of death: from morning, namely, I was speaking, even tonight you will make an end of me, in death. And then, not dying, I hoped, again, till morning, so that simultaneously with death the sorrow of sickness was ended; nonetheless, as a lion so has he, infirmity or God himself through the sorrow of sickness, broken all my bones: if I lie down to sleep, I shall say: when shall I rise? And again, I shall look for the evening, and shall be filled with sorrows even till darkness (Job 7:4).",
      "takeaway": "",
      "sourceId": "hcf:source:historicalchristian-faith",
      "rank": 60,
      "tags": [
        "hcf",
        "c1274"
      ],
      "targetVerseId": "kjva:isaiah.38.13"
    }
  ]
}
