{
  "chapter": {
    "id": "rus-synodal:psalms.58",
    "translationId": "rus-synodal",
    "bookSlug": "psalms",
    "chapterNumber": 58,
    "referenceLabel": "Psalms 58",
    "summary": "Source text for Psalms 58 in Russian Synodal Translation."
  },
  "verses": [
    {
      "id": "rus-synodal:psalms.58.1",
      "translationId": "rus-synodal",
      "bookSlug": "psalms",
      "chapterNumber": 58,
      "verseNumber": 1,
      "referenceLabel": "Psalms 58:1",
      "text": "Начальнику хора. Не погуби. Писание Давида, когда Саул послал стеречь дом его, чтобы умертвить его.",
      "paragraphStart": true
    },
    {
      "id": "rus-synodal:psalms.58.2",
      "translationId": "rus-synodal",
      "bookSlug": "psalms",
      "chapterNumber": 58,
      "verseNumber": 2,
      "referenceLabel": "Psalms 58:2",
      "text": "Избавь меня от врагов моих, Боже мой! защити меня от восстающих на меня;",
      "paragraphStart": false
    },
    {
      "id": "rus-synodal:psalms.58.3",
      "translationId": "rus-synodal",
      "bookSlug": "psalms",
      "chapterNumber": 58,
      "verseNumber": 3,
      "referenceLabel": "Psalms 58:3",
      "text": "избавь меня от делающих беззаконие; спаси от кровожадных,",
      "paragraphStart": false
    },
    {
      "id": "rus-synodal:psalms.58.4",
      "translationId": "rus-synodal",
      "bookSlug": "psalms",
      "chapterNumber": 58,
      "verseNumber": 4,
      "referenceLabel": "Psalms 58:4",
      "text": "ибо вот, они подстерегают душу мою; собираются на меня сильные не за преступление мое и не за грех мой, Господи;",
      "paragraphStart": false
    },
    {
      "id": "rus-synodal:psalms.58.5",
      "translationId": "rus-synodal",
      "bookSlug": "psalms",
      "chapterNumber": 58,
      "verseNumber": 5,
      "referenceLabel": "Psalms 58:5",
      "text": "без вины моей сбегаются и вооружаются; подвигнись на помощь мне и воззри.",
      "paragraphStart": false
    },
    {
      "id": "rus-synodal:psalms.58.6",
      "translationId": "rus-synodal",
      "bookSlug": "psalms",
      "chapterNumber": 58,
      "verseNumber": 6,
      "referenceLabel": "Psalms 58:6",
      "text": "Ты, Господи, Боже сил, Боже Израилев, восстань посетить все народы, не пощади ни одного из нечестивых беззаконников:",
      "paragraphStart": false
    },
    {
      "id": "rus-synodal:psalms.58.7",
      "translationId": "rus-synodal",
      "bookSlug": "psalms",
      "chapterNumber": 58,
      "verseNumber": 7,
      "referenceLabel": "Psalms 58:7",
      "text": "вечером возвращаются они, воют, как псы, и ходят вокруг города;",
      "paragraphStart": false
    },
    {
      "id": "rus-synodal:psalms.58.8",
      "translationId": "rus-synodal",
      "bookSlug": "psalms",
      "chapterNumber": 58,
      "verseNumber": 8,
      "referenceLabel": "Psalms 58:8",
      "text": "вот они изрыгают хулу языком своим; в устах их мечи: \"ибо\", думают они, \"кто слышит?\"",
      "paragraphStart": false
    },
    {
      "id": "rus-synodal:psalms.58.9",
      "translationId": "rus-synodal",
      "bookSlug": "psalms",
      "chapterNumber": 58,
      "verseNumber": 9,
      "referenceLabel": "Psalms 58:9",
      "text": "Но Ты, Господи, посмеешься над ними; Ты посрамишь все народы.",
      "paragraphStart": false
    },
    {
      "id": "rus-synodal:psalms.58.10",
      "translationId": "rus-synodal",
      "bookSlug": "psalms",
      "chapterNumber": 58,
      "verseNumber": 10,
      "referenceLabel": "Psalms 58:10",
      "text": "Сила - у них, но я к Тебе прибегаю, ибо Бог - заступник мой.",
      "paragraphStart": false
    },
    {
      "id": "rus-synodal:psalms.58.11",
      "translationId": "rus-synodal",
      "bookSlug": "psalms",
      "chapterNumber": 58,
      "verseNumber": 11,
      "referenceLabel": "Psalms 58:11",
      "text": "Бой мой, милующий меня, предварит меня; Бог даст мне смотреть на врагов моих.",
      "paragraphStart": false
    },
    {
      "id": "rus-synodal:psalms.58.12",
      "translationId": "rus-synodal",
      "bookSlug": "psalms",
      "chapterNumber": 58,
      "verseNumber": 12,
      "referenceLabel": "Psalms 58:12",
      "text": "Не умерщвляй их, чтобы не забыл народ мой; расточи их силою Твоею и низложи их, Господи, защитник наш.",
      "paragraphStart": false
    },
    {
      "id": "rus-synodal:psalms.58.13",
      "translationId": "rus-synodal",
      "bookSlug": "psalms",
      "chapterNumber": 58,
      "verseNumber": 13,
      "referenceLabel": "Psalms 58:13",
      "text": "Слово языка их есть грех уст их, да уловятся они в гордости своей за клятву и ложь, которую произносят.",
      "paragraphStart": false
    },
    {
      "id": "rus-synodal:psalms.58.14",
      "translationId": "rus-synodal",
      "bookSlug": "psalms",
      "chapterNumber": 58,
      "verseNumber": 14,
      "referenceLabel": "Psalms 58:14",
      "text": "Расточи их во гневе, расточи, чтобы их не было; и да познают, что Бог владычествует над Иаковом до пределов земли.",
      "paragraphStart": false
    },
    {
      "id": "rus-synodal:psalms.58.15",
      "translationId": "rus-synodal",
      "bookSlug": "psalms",
      "chapterNumber": 58,
      "verseNumber": 15,
      "referenceLabel": "Psalms 58:15",
      "text": "Пусть возвращаются вечером, воют, как псы, и ходят вокруг города;",
      "paragraphStart": false
    },
    {
      "id": "rus-synodal:psalms.58.16",
      "translationId": "rus-synodal",
      "bookSlug": "psalms",
      "chapterNumber": 58,
      "verseNumber": 16,
      "referenceLabel": "Psalms 58:16",
      "text": "пусть бродят, чтобы найти пищу, и несытые проводят ночи.",
      "paragraphStart": false
    },
    {
      "id": "rus-synodal:psalms.58.17",
      "translationId": "rus-synodal",
      "bookSlug": "psalms",
      "chapterNumber": 58,
      "verseNumber": 17,
      "referenceLabel": "Psalms 58:17",
      "text": "А я буду воспевать силу Твою и с раннего утра провозглашать милость Твою, ибо Ты был мне защитою и убежищем в день бедствия моего.",
      "paragraphStart": false
    },
    {
      "id": "rus-synodal:psalms.58.18",
      "translationId": "rus-synodal",
      "bookSlug": "psalms",
      "chapterNumber": 58,
      "verseNumber": 18,
      "referenceLabel": "Psalms 58:18",
      "text": "Сила моя! Тебя буду воспевать я, ибо Бог - заступник мой, Бог мой, милующий меня.",
      "paragraphStart": false
    }
  ]
}
